compas_notebook/__init__.py
compas_notebook/__main__.py
compas_notebook/config.py
compas_notebook/controller.py
compas_notebook/viewer.py
compas_notebook/conversions/__init__.py
compas_notebook/conversions/buffers.py
compas_notebook/conversions/colors.py
compas_notebook/conversions/geometry.py
compas_notebook/conversions/graphs.py
compas_notebook/conversions/meshes.py
compas_notebook/geometry/__init__.py
compas_notebook/geometry/dot.py
compas_notebook/scene/__init__.py
compas_notebook/scene/boxobject.py
compas_notebook/scene/brepobject.py
compas_notebook/scene/capsuleobject.py
compas_notebook/scene/circleobject.py
compas_notebook/scene/coneobject.py
compas_notebook/scene/curveobject.py
compas_notebook/scene/cylinderobject.py
compas_notebook/scene/dotobject.py
compas_notebook/scene/ellipseobject.py
compas_notebook/scene/frameobject.py
compas_notebook/scene/graphobject.py
compas_notebook/scene/groupobject.py
compas_notebook/scene/lineobject.py
compas_notebook/scene/meshobject.py
compas_notebook/scene/planeobject.py
compas_notebook/scene/pointcloudobject.py
compas_notebook/scene/pointobject.py
compas_notebook/scene/polygonobject.py
compas_notebook/scene/polyhedronobject.py
compas_notebook/scene/polylineobject.py
compas_notebook/scene/scene.py
compas_notebook/scene/sceneobject.py
compas_notebook/scene/sphereobject.py
compas_notebook/scene/surfaceobject.py
compas_notebook/scene/torusobject.py
compas_notebook/scene/vectorobject.py
compas_notebook/widgets/__init__.py
compas_notebook/widgets/widget.py
compas_notebook-0.11.0.dist-info/licenses/LICENSE
compas_notebook-0.11.0.dist-info/METADATA
compas_notebook-0.11.0.dist-info/WHEEL
compas_notebook-0.11.0.dist-info/top_level.txt
compas_notebook-0.11.0.dist-info/RECORD
